{
  "jss.js": {
    "bundled": 63967,
    "minified": 23438,
    "gzipped": 7131
  },
  "jss.min.js": {
    "bundled": 62580,
    "minified": 22669,
    "gzipped": 6779
  },
  "jss.cjs.js": {
    "bundled": 59498,
    "minified": 26181,
    "gzipped": 7202
  },
  "jss.esm.mjs": {
    "bundled": 57910,
    "minified": 24909,
    "gzipped": 7030,
    "treeshaked": {
      "rollup": {
        "code": 20343,
        "import_statements": 345
      },
      "webpack": {
        "code": 21826
      }
    }
  }
}
