{
  "dist/jss.js": {
    "bundled": 56541,
    "minified": 21282,
    "gzipped": 6440
  },
  "dist/jss.min.js": {
    "bundled": 55665,
    "minified": 20667,
    "gzipped": 6125
  },
  "dist/jss.cjs.js": {
    "bundled": 50140,
    "minified": 21903,
    "gzipped": 6191
  },
  "dist/jss.esm.js": {
    "bundled": 49683,
    "minified": 21531,
    "gzipped": 6105,
    "treeshaked": {
      "rollup": {
        "code": 18438,
        "import_statements": 189
      },
      "webpack": {
        "code": 19789
      }
    }
  }
}
