{
  "dist/jss.js": {
    "bundled": 59273,
    "minified": 22057,
    "gzipped": 6633
  },
  "dist/jss.min.js": {
    "bundled": 57866,
    "minified": 21259,
    "gzipped": 6269
  },
  "dist/jss.cjs.js": {
    "bundled": 54344,
    "minified": 23853,
    "gzipped": 6655
  },
  "dist/jss.esm.js": {
    "bundled": 53828,
    "minified": 23429,
    "gzipped": 6566,
    "treeshaked": {
      "rollup": {
        "code": 19318,
        "import_statements": 281
      },
      "webpack": {
        "code": 20740
      }
    }
  }
}
