{
  "jss.js": {
    "bundled": 65164,
    "minified": 23227,
    "gzipped": 7222
  },
  "jss.min.js": {
    "bundled": 63768,
    "minified": 22458,
    "gzipped": 6877
  },
  "jss.cjs.js": {
    "bundled": 60832,
    "minified": 26255,
    "gzipped": 7336
  },
  "jss.esm.js": {
    "bundled": 59204,
    "minified": 24949,
    "gzipped": 7171,
    "treeshaked": {
      "rollup": {
        "code": 20213,
        "import_statements": 345
      },
      "webpack": {
        "code": 21703
      }
    }
  }
}
