{
  "jss-plugin-global.js": {
    "bundled": 5406,
    "minified": 2331,
    "gzipped": 962
  },
  "jss-plugin-global.min.js": {
    "bundled": 5406,
    "minified": 2331,
    "gzipped": 962
  },
  "jss-plugin-global.cjs.js": {
    "bundled": 4659,
    "minified": 2457,
    "gzipped": 932
  },
  "jss-plugin-global.esm.js": {
    "bundled": 4313,
    "minified": 2183,
    "gzipped": 827,
    "treeshaked": {
      "rollup": {
        "code": 55,
        "import_statements": 55
      },
      "webpack": {
        "code": 1072
      }
    }
  }
}
