{
  "dist/react-jss.js": {
    "bundled": 167788,
    "minified": 58057,
    "gzipped": 18916
  },
  "dist/react-jss.min.js": {
    "bundled": 111063,
    "minified": 41411,
    "gzipped": 13978
  },
  "dist/react-jss.cjs.js": {
    "bundled": 26174,
    "minified": 11471,
    "gzipped": 3751
  },
  "dist/react-jss.esm.js": {
    "bundled": 25212,
    "minified": 10636,
    "gzipped": 3624,
    "treeshaked": {
      "rollup": {
        "code": 1946,
        "import_statements": 538
      },
      "webpack": {
        "code": 3544
      }
    }
  }
}
