{
  "react-jss.js": {
    "bundled": 165404,
    "minified": 58001,
    "gzipped": 19085
  },
  "react-jss.min.js": {
    "bundled": 108044,
    "minified": 41207,
    "gzipped": 14048
  },
  "react-jss.cjs.js": {
    "bundled": 23517,
    "minified": 10606,
    "gzipped": 3416
  },
  "react-jss.esm.js": {
    "bundled": 21158,
    "minified": 8759,
    "gzipped": 3179,
    "treeshaked": {
      "rollup": {
        "code": 1815,
        "import_statements": 566
      },
      "webpack": {
        "code": 3464
      }
    }
  }
}
