{
  "dist/jss-starter-kit.js": {
    "bundled": 82275,
    "minified": 33215,
    "gzipped": 9533
  },
  "dist/jss-starter-kit.min.js": {
    "bundled": 81408,
    "minified": 32763,
    "gzipped": 9318
  },
  "dist/jss-starter-kit.cjs.js": {
    "bundled": 2523,
    "minified": 2309,
    "gzipped": 697
  },
  "dist/jss-starter-kit.esm.js": {
    "bundled": 1447,
    "minified": 1335,
    "gzipped": 466,
    "treeshaked": {
      "rollup": {
        "code": 854,
        "import_statements": 559
      },
      "webpack": {
        "code": 2390
      }
    }
  }
}
